fishknn/__init__.py
fishknn/app.py
fishknn/common.py
fishknn/help.py
growKNN4fish-3.1.1.dist-info/METADATA
growKNN4fish-3.1.1.dist-info/WHEEL
growKNN4fish-3.1.1.dist-info/entry_points.txt
growKNN4fish-3.1.1.dist-info/top_level.txt
growKNN4fish-3.1.1.dist-info/RECORD
