Metadata-Version: 2.1
Name: growKNN4fish
Version: 3.1.1
Summary: growable fish classifier, KNN
Author-email: Mingk42 <xoals123456t@gmail.com>
License: MIT
Project-URL: hompage, https://github.com/Mingk42/fishKNN
Project-URL: issue, https://github.com/Mingk42/fishKNN/issues
Requires-Python: >=3.9
Requires-Dist: scikit-learn>=1.5.1
Requires-Dist: pandas>=2.2.2
Requires-Dist: plotext>=5.2.8
